vgsstyle/__init__.py
vgsstyle/cli.py
vgsstyle/config.py
vgsstyle/linters/__init__.py
vgsstyle/linters/base.py
vgsstyle/linters/black.py
vgsstyle/linters/flake.py
vgs_style-1.1.0.dist-info/entry_points.txt
vgs_style-1.1.0.dist-info/LICENSE
vgs_style-1.1.0.dist-info/WHEEL
vgs_style-1.1.0.dist-info/METADATA
vgs_style-1.1.0.dist-info/RECORD
