Metadata-Version: 2.1
Name: vgs-style
Version: 1.1.0
Summary: Library for linting and formatting Python source code
Author: Petro Melnykov
Author-email: petro.melnykov@vgs.io
Requires-Python: >=3.6.1,<4
Classifier: Programming Language :: Python :: 3
Classifier: Programming Language :: Python :: 3.10
Classifier: Programming Language :: Python :: 3.7
Classifier: Programming Language :: Python :: 3.8
Classifier: Programming Language :: Python :: 3.9
Requires-Dist: black (>=20.8b1,<21.0)
Requires-Dist: click (>6,<9)
Requires-Dist: flake8 (>=4,<5)
Requires-Dist: flake8-import-order (>=0.18.1,<0.19.0)
Requires-Dist: pydantic (>=1.8.2,<2.0.0)
Requires-Dist: toml (>=0.10.2,<0.11.0)
